[{"label":"study","frequent":40},{"label":"motion","frequent":15},{"label":"forces","frequent":10},{"label":"electricity","frequent":15},{"label":"movement","frequent":10},{"label":"relation","frequent":5},{"label":"things","frequent":10},{"label":"force","frequent":5},{"label":"ad","frequent":5},{"label":"energy","frequent":85},{"label":"living","frequent":5},{"label":"nonliving","frequent":5},{"label":"laws","frequent":15},{"label":"speed","frequent":45},{"label":"velocity","frequent":30},{"label":"define","frequent":5},{"label":"constraints","frequent":5},{"label":"universe","frequent":10},{"label":"physics","frequent":120},{"label":"describing","frequent":5},{"label":"matter","frequent":90},{"label":"physics-the","frequent":5},{"label":"world","frequent":10},{"label":"works","frequent":10},{"label":"science","frequent":70},{"label":"interactions","frequent":30},{"label":"studies","frequent":5},{"label":"properties","frequent":45},{"label":"nature","frequent":40},{"label":"branch","frequent":30},{"label":"concerned","frequent":25},{"label":"source","frequent":40},{"label":"google","frequent":10},{"label":"defintions","frequent":5},{"label":"two","frequent":15},{"label":"grouped","frequent":15},{"label":"traditional","frequent":15},{"label":"fields","frequent":15},{"label":"acoustics","frequent":15},{"label":"optics","frequent":15},{"label":"mechanics","frequent":20},{"label":"thermodynamics","frequent":15},{"label":"electromagnetism","frequent":15},{"label":"modern","frequent":15},{"label":"extensions","frequent":15},{"label":"thefreedictionary","frequent":15},{"label":"interaction","frequent":15},{"label":"org","frequent":25},{"label":"answers","frequent":5},{"label":"natural","frequent":15},{"label":"objects","frequent":5},{"label":"treats","frequent":10},{"label":"acting","frequent":5},{"label":"department","frequent":5},{"label":"gravitation","frequent":5},{"label":"heat","frequent":10},{"label":"light","frequent":10},{"label":"magnetism","frequent":10},{"label":"modify","frequent":5},{"label":"general","frequent":10},{"label":"bodies","frequent":5},{"label":"philosophy","frequent":5},{"label":"brainyquote","frequent":5},{"label":"words","frequent":5},{"label":"ph","frequent":5},{"label":"html","frequent":5},{"label":"lrl","frequent":5},{"label":"zgzmeylfwuy","frequent":5},{"label":"subject","frequent":5},{"label":"distinguished","frequent":5},{"label":"chemistry","frequent":5},{"label":"biology","frequent":5},{"label":"includes","frequent":5},{"label":"radiation","frequent":5},{"label":"sound","frequent":5},{"label":"structure","frequent":5},{"label":"atoms","frequent":5},{"label":"including","frequent":10},{"label":"atomic","frequent":10},{"label":"nuclear","frequent":10},{"label":"cryogenics","frequent":10},{"label":"solid-state","frequent":10},{"label":"particle","frequent":10},{"label":"plasma","frequent":10},{"label":"deals","frequent":5},{"label":"merriam-webster","frequent":5},{"label":"dictionary","frequent":10},{"label":"analysis","frequent":5},{"label":"conducted","frequent":5},{"label":"order","frequent":5},{"label":"understand","frequent":5},{"label":"behaves","frequent":5},{"label":"en","frequent":5},{"label":"wikipedia","frequent":5},{"label":"wiki","frequent":5},{"label":"physics-","frequent":5},{"label":"physical","frequent":5},{"label":"behaviour","frequent":5},{"label":"collinsdictionary","frequent":5},{"label":"english","frequent":5},{"label":"time","frequent":35},{"label":"distance","frequent":35},{"label":"wheels","frequent":5},{"label":"revelations","frequent":5},{"label":"minute","frequent":5},{"label":"acceleration","frequent":20},{"label":"torque","frequent":5},{"label":"wheel","frequent":5},{"label":"rotations","frequent":5},{"label":"resistance","frequent":5},{"label":"momentum","frequent":5},{"label":"measure","frequent":10},{"label":"direction","frequent":10},{"label":"car","frequent":5},{"label":"add","frequent":5},{"label":"traveled","frequent":5},{"label":"weight","frequent":5},{"label":"electrical","frequent":5},{"label":"power","frequent":5}]